{
  "en_rpeid": "4000",
  "en_st": 4,
  "en_naz": "VE 4000 - LJUBLJANA BEŽIGRAD",
  "rpeid": "4006",
  "st": 6,
  "naz": "VO 4006 - LJUBLJANA MOSTE-POLJE 2",
  "vol": [
    {
      "st": 15,
      "rpeid": "015",
      "naz": "Dom občanov Fužine, Preglov trg 15",
      "rez": null,
      "udel": {
        "upr": 883,
        "gl": 527,
        "prc": 0.5968
      },
      "prestetih_glasov": null
    },
    {
      "st": 16,
      "rpeid": "016",
      "naz": "Dom občanov Fužine, Preglov trg 15",
      "rez": null,
      "udel": {
        "upr": 791,
        "gl": 370,
        "prc": 0.4678
      },
      "prestetih_glasov": null
    },
    {
      "st": 5,
      "rpeid": "005",
      "naz": "OŠ Božidarja Jakca, Nusdorferjeva ul. 10",
      "rez": null,
      "udel": {
        "upr": 615,
        "gl": 310,
        "prc": 0.5041
      },
      "prestetih_glasov": null
    },
    {
      "st": 7,
      "rpeid": "007",
      "naz": "OŠ Božidarja Jakca, Nusdorferjeva ul. 10",
      "rez": null,
      "udel": {
        "upr": 661,
        "gl": 324,
        "prc": 0.4902
      },
      "prestetih_glasov": null
    },
    {
      "st": 8,
      "rpeid": "008",
      "naz": "OŠ Božidarja Jakca, Nusdorferjeva ul. 10",
      "rez": null,
      "udel": {
        "upr": 610,
        "gl": 300,
        "prc": 0.4918
      },
      "prestetih_glasov": null
    },
    {
      "st": 10,
      "rpeid": "010",
      "naz": "OŠ Božidarja Jakca, Nusdorferjeva ul. 10",
      "rez": null,
      "udel": {
        "upr": 906,
        "gl": 474,
        "prc": 0.5232
      },
      "prestetih_glasov": null
    },
    {
      "st": 11,
      "rpeid": "011",
      "naz": "OŠ Božidarja Jakca, Nusdorferjeva ul. 10",
      "rez": null,
      "udel": {
        "upr": 477,
        "gl": 237,
        "prc": 0.4969
      },
      "prestetih_glasov": null
    },
    {
      "st": 12,
      "rpeid": "012",
      "naz": "OŠ Božidarja Jakca, Nusdorferjeva ul. 10",
      "rez": null,
      "udel": {
        "upr": 349,
        "gl": 173,
        "prc": 0.4957
      },
      "prestetih_glasov": null
    },
    {
      "st": 1,
      "rpeid": "001",
      "naz": "OŠ Karla Destovnika Kajuha, Jakčeva ul. 42",
      "rez": null,
      "udel": {
        "upr": 470,
        "gl": 230,
        "prc": 0.4894
      },
      "prestetih_glasov": null
    },
    {
      "st": 2,
      "rpeid": "002",
      "naz": "OŠ Karla Destovnika Kajuha, Jakčeva ul. 42",
      "rez": null,
      "udel": {
        "upr": 436,
        "gl": 215,
        "prc": 0.4931
      },
      "prestetih_glasov": null
    },
    {
      "st": 3,
      "rpeid": "003",
      "naz": "OŠ Karla Destovnika Kajuha, Jakčeva ul. 42",
      "rez": null,
      "udel": {
        "upr": 527,
        "gl": 251,
        "prc": 0.4763
      },
      "prestetih_glasov": null
    },
    {
      "st": 4,
      "rpeid": "004",
      "naz": "OŠ Karla Destovnika Kajuha, Jakčeva ul. 42",
      "rez": null,
      "udel": {
        "upr": 531,
        "gl": 268,
        "prc": 0.5047
      },
      "prestetih_glasov": null
    },
    {
      "st": 13,
      "rpeid": "013",
      "naz": "OŠ Martina Krpana, Gašperšičeva ul. 10",
      "rez": null,
      "udel": {
        "upr": 775,
        "gl": 430,
        "prc": 0.5548
      },
      "prestetih_glasov": null
    },
    {
      "st": 14,
      "rpeid": "014",
      "naz": "OŠ Martina Krpana, Gašperšičeva ul. 10",
      "rez": null,
      "udel": {
        "upr": 745,
        "gl": 392,
        "prc": 0.5262
      },
      "prestetih_glasov": null
    },
    {
      "st": 17,
      "rpeid": "017",
      "naz": "OŠ Nove Fužine, Preglov trg 8",
      "rez": null,
      "udel": {
        "upr": 657,
        "gl": 338,
        "prc": 0.5145
      },
      "prestetih_glasov": null
    },
    {
      "st": 18,
      "rpeid": "018",
      "naz": "OŠ Nove Fužine, Preglov trg 8",
      "rez": null,
      "udel": {
        "upr": 960,
        "gl": 284,
        "prc": 0.2958
      },
      "prestetih_glasov": null
    },
    {
      "st": 19,
      "rpeid": "019",
      "naz": "OŠ Nove Fužine, Preglov trg 8",
      "rez": null,
      "udel": {
        "upr": 990,
        "gl": 525,
        "prc": 0.5303
      },
      "prestetih_glasov": null
    },
    {
      "st": 21,
      "rpeid": "021",
      "naz": "OŠ Nove Fužine, Preglov trg 8",
      "rez": null,
      "udel": {
        "upr": 874,
        "gl": 455,
        "prc": 0.5206
      },
      "prestetih_glasov": null
    },
    {
      "st": 20,
      "rpeid": "020",
      "naz": "SŠ za Gastronomijo in turizem Lj., Preglov trg 9",
      "rez": null,
      "udel": {
        "upr": 756,
        "gl": 410,
        "prc": 0.5423
      },
      "prestetih_glasov": null
    },
    {
      "st": 22,
      "rpeid": "022",
      "naz": "SŠ za Gastronomijo in turizem Lj., Preglov trg 9",
      "rez": null,
      "udel": {
        "upr": 712,
        "gl": 413,
        "prc": 0.5801
      },
      "prestetih_glasov": null
    },
    {
      "st": 901,
      "rpeid": "901",
      "naz": "Predčasno glasovanje",
      "rez": null,
      "udel": {
        "upr": 0,
        "gl": 0,
        "prc": 0.0
      },
      "prestetih_glasov": null
    }
  ],
  "liste": [
    {
      "ime": "Nedeljko",
      "pri": "Todorović",
      "st": 107752,
      "naz": "DRŽAVLJANSKO GIBANJE RESNI.CA",
      "knaz": "RESNI.CA",
      "hcol": "7e5096"
    },
    {
      "ime": "Matjaž",
      "pri": "Majnik",
      "st": 107759,
      "naz": "MI, SOCIALISTI!",
      "knaz": "MI, SOCIALISTI!",
      "hcol": "fb4c48"
    },
    {
      "ime": "Jasmina",
      "pri": "Peterle",
      "st": 107750,
      "naz": "GLAS UPOKOJENCEV PAVLA RUPARJA",
      "knaz": "GLAS UPOKOJENCEV",
      "hcol": "020437"
    },
    {
      "ime": "Dalibor",
      "pri": "Pejičić",
      "st": 107757,
      "naz": "SLOVENSKA DEMOKRATSKA STRANKA - SDS",
      "knaz": "SDS",
      "hcol": "FFE53F"
    },
    {
      "ime": "Milan",
      "pri": "Jakopovič",
      "st": 107760,
      "naz": "LEVICA IN VESNA",
      "knaz": "LEVICA IN VESNA",
      "hcol": "b30020"
    },
    {
      "ime": "Sonja",
      "pri": "Smrekar",
      "st": 107799,
      "naz": "KARL ERJAVEC STRANKA ZAUPANJE",
      "knaz": "ZAUPANJE",
      "hcol": "89aedb"
    },
    {
      "pfx": "dr.",
      "ime": "Dragan",
      "pri": "Matić",
      "st": 107761,
      "naz": "PREROD - STRANKA VLADIMIRJA PREBILIČA",
      "knaz": "PREROD",
      "hcol": "ed0990"
    },
    {
      "pfx": "mag.",
      "ime": "Marko",
      "pri": "Koprivc",
      "st": 107753,
      "naz": "SOCIALNI DEMOKRATI",
      "knaz": "SD",
      "hcol": "cb000d"
    },
    {
      "ime": "Rok",
      "pri": "Kokalj",
      "st": 107756,
      "naz": "PIRATSKA STRANKA SLOVENIJE",
      "knaz": "PIRATI",
      "hcol": "000000"
    },
    {
      "ime": "Janez",
      "pri": "Žagar",
      "st": 107749,
      "naz": "NOVA SLOVENIJA, SLOVENSKA LJUDSKA STRANKA, FOKUS MARKA LOTRIČA",
      "knaz": "NSi, SLS, FOKUS",
      "hcol": "009ac7"
    },
    {
      "ime": "Lenart",
      "pri": "Žavbi",
      "st": 107754,
      "naz": "GIBANJE SVOBODA",
      "knaz": "SVOBODA",
      "hcol": "0063a6"
    },
    {
      "ime": "Marko Mitja",
      "pri": "Feguš",
      "st": 107758,
      "naz": "ZELENI SLOVENIJE + SG STRANKA GENERACIJ",
      "knaz": "ZELENI+SG",
      "hcol": "75a948"
    },
    {
      "ime": "Nataša",
      "pri": "Jerman",
      "st": 107803,
      "naz": "SLOGA",
      "knaz": "SLOGA",
      "hcol": "023463"
    },
    {
      "st": 107801,
      "naz": "REŠITEV - STRANKA UPOKOJENCEV VELENJE, SLOVENIJA",
      "knaz": "REŠITEV",
      "hcol": "ADA702"
    },
    {
      "ime": "Damjan",
      "pri": "Stanek",
      "st": 107755,
      "naz": "DEMOKRATI. ANŽETA LOGARJA",
      "knaz": "DEMOKRATI.",
      "hcol": "01beac"
    },
    {
      "ime": "Laura",
      "pri": "Miklič",
      "st": 107751,
      "naz": "SLOVENSKA NACIONALNA STRANKA - SNS",
      "knaz": "SNS",
      "hcol": "4d4d4d"
    },
    {
      "ime": "Žiga",
      "pri": "Pavšič",
      "st": 107800,
      "naz": "KOALICIJA ALTERNATIVA ZA SLOVENIJO (STRANKA NIČ OD TEGA IN STRANKA ZA ZDRAVO DRUŽBO)",
      "knaz": "ALTERNATIVA",
      "hcol": "F3808A"
    }
  ],
  "nastavitve": {
    "timestamp": "2026-03-22T16:58:37Z",
    "datum": "2026-03-22T17:30:00Z",
    "cas_udelezba": "16:00",
    "has_udelezba": true,
    "has_rezultat": false,
    "is_final": false,
    "has_rezultat_kandidati": false,
    "has_kandidati_mandati": false,
    "has_kandidati_removed": false
  }
}
